lltk
