Metadata-Version: 1.1
Name: lltk
Version: 0.2.3
Summary: The Language Learning Toolkit (LLTK) performs a variety of tasks useful for (human) language learning.
Home-page: http://github.com/lltk/lltk
Author: Markus Beuckelmann
Author-email: email@markus-beuckelmann.de
License: LGPL
Keywords: language learning toolkit lltk
Platform: UNKNOWN
Classifier: Development Status :: 3 - Alpha
Classifier: Intended Audience :: Education
Classifier: Intended Audience :: Developers
Classifier: Intended Audience :: Science/Research
Classifier: License :: OSI Approved :: GNU Lesser General Public License v3 (LGPLv3)
Classifier: Natural Language :: Dutch
Classifier: Natural Language :: English
Classifier: Natural Language :: French
Classifier: Natural Language :: German
Classifier: Natural Language :: Italian
Classifier: Natural Language :: Spanish
Classifier: Operating System :: OS Independent
Classifier: Programming Language :: Python
Classifier: Topic :: Software Development :: Libraries :: Python Modules
Classifier: Topic :: Text Processing :: Linguistic
